patsy/__init__.py
patsy/build.py
patsy/builtins.py
patsy/categorical.py
patsy/compat.py
patsy/compat_ordereddict.py
patsy/constraint.py
patsy/contrasts.py
patsy/desc.py
patsy/design_info.py
patsy/eval.py
patsy/highlevel.py
patsy/infix_parser.py
patsy/mgcv_cubic_splines.py
patsy/missing.py
patsy/origin.py
patsy/parse_formula.py
patsy/redundancy.py
patsy/splines.py
patsy/state.py
patsy/test_build.py
patsy/test_highlevel.py
patsy/test_regressions.py
patsy/test_splines_bs_data.py
patsy/test_splines_crs_data.py
patsy/test_state.py
patsy/tokens.py
patsy/user_util.py
patsy/util.py
patsy/version.py
patsy-1.0.0.dist-info/LICENSE.txt
patsy-1.0.0.dist-info/METADATA
patsy-1.0.0.dist-info/WHEEL
patsy-1.0.0.dist-info/top_level.txt
patsy-1.0.0.dist-info/RECORD
